flowpipe_editor/__init__.py
flowpipe_editor/flowpipe_editor_widget.py
flowpipe_editor/icons/3dequalizer.png
flowpipe_editor/icons/flowpipe.png
flowpipe_editor/icons/houdini.png
flowpipe_editor/icons/mari.png
flowpipe_editor/icons/maya.png
flowpipe_editor/icons/nuke.png
flowpipe_editor/icons/python.png
flowpipe_editor/widgets/__init__.py
flowpipe_editor/widgets/dark_theme.py
flowpipe_editor/widgets/properties_bin/__init__.py
flowpipe_editor/widgets/properties_bin/attribute_widgets.py
flowpipe_editor/widgets/properties_bin/attributes_widget.py
flowpipe_editor/widgets/properties_bin/description.py
flowpipe_editor/widgets/properties_bin/metadata_widget.py
flowpipe_editor/widgets/properties_bin/node_property_widgets.py
flowpipe_editor-1.0.5.dist-info/LICENSE
flowpipe_editor-1.0.5.dist-info/METADATA
flowpipe_editor-1.0.5.dist-info/WHEEL
flowpipe_editor-1.0.5.dist-info/entry_points.txt
flowpipe_editor-1.0.5.dist-info/RECORD
