Metadata-Version: 2.3
Name: flowpipe_editor
Version: 1.0.5
Summary: A lightweight framework for flow-based programming in python.
License: MIT
Author: Jonas Sorgenfrei
Author-email: jonas_sorgenfrei@yahoo.de
Requires-Python: >=3.9
Classifier: License :: OSI Approved :: MIT License
Classifier: Programming Language :: Python
Classifier: Programming Language :: Python :: 3
Classifier: Programming Language :: Python :: 3.9
Classifier: Programming Language :: Python :: 3.10
Classifier: Programming Language :: Python :: 3.11
Classifier: Programming Language :: Python :: 3.12
Classifier: Programming Language :: Python :: 3.13
Classifier: Programming Language :: Python :: 3.8
Requires-Dist: NodeGraphQt (>=0.6.3,<0.7.0)
Requires-Dist: Qt.py (>=1.4.6,<2.0.0)
Requires-Dist: ascii-canvas (>=2.0.0)
Requires-Dist: flowpipe (>=1.0.4,<2.0.0)
Project-URL: Repository, https://github.com/jonassorgenfrei/flowpipe-editor
